{
    "ports": {
        "2048.zip": 53392,
        "a7xpg.zip": 3018,
        "abbayedesmorts.zip": 2049,
        "abes_adventure.zip": 9210,
        "abombniball.zip": 2109,
        "absolutereflex.zip": 2044,
        "abuse.zip": 16912,
        "aerofoil.zip": 658,
        "afternoonstalker.zip": 681,
        "air.zip": 1102,
        "akeyspath.zip": 4746,
        "alchemyquest.zip": 3037,
        "alephone-marathon.zip": 13708,
        "alephone-marathon2.zip": 8633,
        "alephone-marathoninfinity.zip": 8539,
        "alienblaster.zip": 4271,
        "alienpogs.zip": 460,
        "aliensquatter.zip": 1722,
        "alruna.zip": 584,
        "am2r.zip": 32064,
        "ametadatagame.zip": 1417,
        "anarch.zip": 4456,
        "angband.zip": 2527,
        "annalynn.zip": 792,
        "annulus.zip": 87,
        "anodyne.zip": 4159,
        "antonballclassic.zip": 266,
        "apocrunner.zip": 3802,
        "apondbeyond.zip": 237,
        "apotris.zip": 32039,
        "apricots.zip": 2672,
        "aquaria.zip": 356,
        "area2048.zip": 601,
        "arengius.zip": 266,
        "arkovstower.zip": 2653,
        "armagetronad.zip": 2869,
        "assaultshell.zip": 529,
        "asylum.zip": 1045,
        "atomic_automaton.zip": 295,
        "augustus.zip": 4471,
        "avp.zip": 12336,
        "axecop.zip": 646,
        "axiom.verge.zip": 18368,
        "baconthulhu.zip": 388,
        "balatro.zip": 47700,
        "banana.duck.zip": 8033,
        "bananaguy2.zip": 4635,
        "bananaguyclassic.zip": 3025,
        "barbarian.zip": 2154,
        "battalion.zip": 697,
        "bbja.zip": 4622,
        "beardblade.zip": 1027,
        "beat2x.zip": 9033,
        "beatblock.zip": 102,
        "beemisthecurseofgod.zip": 369,
        "belleboomerang.zip": 705,
        "benboquest.zip": 1476,
        "bermuda_syndrome.zip": 4623,
        "billyfrontier.zip": 3538,
        "binarystarinfinity.zip": 399,
        "biolab.zip": 2550,
        "biomassgrowth.zip": 3175,
        "bitsybox.zip": 816,
        "bittriprunner2.zip": 3258,
        "blackout.zip": 1061,
        "blarglike.zip": 63,
        "blastius.zip": 1792,
        "bleed.zip": 5105,
        "bleed2.zip": 5511,
        "blobby.volley2.zip": 7423,
        "bloboats.zip": 712,
        "blobwars.zip": 3214,
        "block.attack.zip": 4133,
        "blockdude_playdate.zip": 1642,
        "blockout2.zip": 5497,
        "blood.zip": 14581,
        "bloodxthirsty.zip": 313,
        "blossomtales2.zip": 4228,
        "bluerevolver.zip": 2160,
        "blues.brothers.zip": 6408,
        "bnbmax.zip": 1829,
        "bnbtourn.zip": 1511,
        "boneraiserminions.zip": 1052,
        "bonesintheboneyard.zip": 169,
        "boni.zip": 937,
        "bootlegbox.zip": 1900,
        "boswars.zip": 2274,
        "botbreak.zip": 3628,
        "botvice.zip": 3920,
        "bowlingcross.zip": 4727,
        "boxspace.zip": 152,
        "bravedogsroad.zip": 1146,
        "breaker.zip": 845,
        "brittleblade.zip": 606,
        "brogue.zip": 2934,
        "brokenpipes.zip": 292,
        "brotato.zip": 2180,
        "brotherbrother.zip": 80,
        "bstone-aog.zip": 8556,
        "bstone-ps.zip": 3655,
        "bugdom.zip": 1373,
        "bugscraper.zip": 2276,
        "bumpersbroadswords.zip": 2659,
        "bunnysflowers.zip": 616,
        "burgerspace.zip": 1260,
        "burst.zip": 1474,
        "butterflysoup.zip": 123,
        "bytepath.zip": 3130,
        "bzflag.zip": 1676,
        "c-dogs.zip": 5565,
        "caidenquest.zip": 1159,
        "cairn.zip": 150,
        "callystrials.zip": 194,
        "candybag.zip": 395,
        "cannonball-lr.zip": 9177,
        "cannonball-st.zip": 7958,
        "cannonball.zip": 3563,
        "cantoi.zip": 95,
        "cardswithpersonalities.zip": 1326,
        "carmageddon.zip": 10212,
        "carriesorderup.zip": 717,
        "cataclysm-dda.zip": 3227,
        "catacomb.zip": 234,
        "catacomb3d.zip": 466,
        "catacomb89.zip": 248,
        "catsonmars.zip": 1436,
        "cattactics.zip": 2865,
        "catwarrior.zip": 1932,
        "cave.story-evo.zip": 28887,
        "cave.story.zip": 18521,
        "cavebuster.zip": 3457,
        "cavecrawler.zip": 1995,
        "caveexpress.zip": 2855,
        "cavepacker.zip": 1471,
        "cceleste.zip": 35195,
        "ceferino.zip": 380,
        "celeste.zip": 27078,
        "chargekid.zip": 2506,
        "chasm.zip": 14622,
        "chessisstupid.zip": 4633,
        "chip.zip": 1854,
        "chipndale.zip": 9758,
        "chroma.zip": 475,
        "chromavescence.zip": 770,
        "circainfinity.zip": 222,
        "cityglitch.zip": 446,
        "clannad.zip": 2029,
        "clashmastery.zip": 909,
        "classicube.zip": 17182,
        "cleavingcaliber.zip": 1016,
        "cliff_hanger.zip": 3725,
        "climb.zip": 774,
        "clockwind.zip": 2504,
        "cmdungeon.zip": 208,
        "cognizance.zip": 183,
        "coincrypt.zip": 282,
        "colorlines.zip": 1386,
        "commander.genius.zip": 11933,
        "cookservedelicious.zip": 737,
        "corsixth.zip": 11505,
        "cosmiccleaning.zip": 680,
        "cosmo-engine.zip": 2717,
        "cosmosmash.zip": 484,
        "cromagrally.zip": 9090,
        "cropsmare.zip": 485,
        "crushborgs.zip": 97,
        "cryptrio.zip": 186,
        "crysalis.zip": 1202,
        "crystalbreaker.zip": 238,
        "crystalsamalgam.zip": 1768,
        "ctp2.zip": 270,
        "curseball.zip": 1897,
        "cursedgem.zip": 229,
        "curseofthearrow.zip": 7935,
        "cybarian.zip": 2385,
        "cyberseraph.zip": 249,
        "daikatana.zip": 3452,
        "darkcrypt.zip": 400,
        "darkdeity.zip": 293,
        "darkmoon.zip": 586,
        "darksheep.zip": 175,
        "davedavedave.zip": 211,
        "davegnukem.zip": 2882,
        "daydreamer.zip": 319,
        "deadicedeluxe.zip": 3578,
        "deadknight.zip": 397,
        "deathchase3d.zip": 403,
        "deathroad.zip": 596,
        "deathroids.zip": 134,
        "deep_sleep.zip": 2202,
        "deeprune.zip": 609,
        "defshot.zip": 1018,
        "deltarune.zip": 3974,
        "demodome.zip": 568,
        "demonizer.zip": 1020,
        "demonkeep.zip": 1015,
        "demonofsakurapass.zip": 770,
        "demonslayer.zip": 169,
        "demonstone64.zip": 501,
        "depthsoflimbo.zip": 1448,
        "derclou.zip": 3767,
        "derelict.zip": 416,
        "descent.zip": 10211,
        "descent2.zip": 7691,
        "descent3.zip": 2186,
        "destructivator.zip": 404,
        "destructivator2.zip": 272,
        "devbootleg.zip": 1230,
        "devilutionx.zip": 41631,
        "dfencervstheorb.zip": 334,
        "digger.zip": 1074,
        "digitaltamersreborn.zip": 442,
        "dinothawr.zip": 4796,
        "discroom.zip": 453,
        "diverdown.zip": 2831,
        "dokimon.zip": 425,
        "domeromantik.zip": 13204,
        "donottakethiscathome.zip": 313,
        "donut.dodo.zip": 2296,
        "doom2d.zip": 2694,
        "doom2rpg.zip": 2934,
        "doom3.zip": 22168,
        "doomengines.zip": 4246,
        "doomrl.zip": 2854,
        "doomrpg.zip": 3251,
        "doukutsu-rs.zip": 1464,
        "downwell.zip": 4851,
        "draculatower.zip": 123,
        "drally.zip": 3544,
        "drbloodshot.zip": 982,
        "drilbertiidiggeredoo.zip": 223,
        "drinkndrive.zip": 353,
        "droid7.zip": 952,
        "ducklingsmaze.zip": 476,
        "dudelingsarcadesportsball.zip": 72,
        "duelingdragons.zip": 497,
        "duke.nukem.3d.zip": 23909,
        "duke3dawo.zip": 6004,
        "dumbasssmartass.zip": 265,
        "dumpyandbumpy.zip": 132,
        "dunelegacy.zip": 443,
        "dungeoncrawlstonesoup.zip": 1960,
        "dungeonrush.zip": 2672,
        "dungeonsouls.zip": 5428,
        "dynamate_playdate.zip": 706,
        "echo_chamber.zip": 14775,
        "edna.zip": 948,
        "eity.zip": 5227,
        "elecdude.zip": 139,
        "elechead.zip": 801,
        "elsewhereinthenight.zip": 218,
        "emojimerge.zip": 3256,
        "endlessdungeon.zip": 1036,
        "enigma.zip": 2103,
        "entropipes.zip": 393,
        "entwined.zip": 410,
        "erebos.zip": 204,
        "escape.zip": 1414,
        "estigma.zip": 763,
        "everpatch.zip": 1864,
        "exhumed.zip": 4914,
        "exilesquadron.zip": 199,
        "exult.zip": 3013,
        "ez.zip": 900,
        "f-zeropocket.zip": 6534,
        "f1race.zip": 3718,
        "f1spirit.zip": 5401,
        "fade_to_black.zip": 2490,
        "faithdemonsiege.zip": 561,
        "fallenleaf.zip": 621,
        "falling_time.zip": 1761,
        "fallout.1.zip": 6,
        "fallout1.zip": 28336,
        "fallout2.zip": 25661,
        "farmner.zip": 5003,
        "feather.park.zip": 6413,
        "fell.zip": 43,
        "fheroes2.zip": 10715,
        "fightorperish.zip": 833,
        "final_quest.zip": 2528,
        "finding_paradise.zip": 2189,
        "fire_and_fondness2.zip": 1270,
        "firearrow.zip": 1332,
        "fireboy.zip": 61,
        "firework.zip": 58,
        "fishfillets.zip": 606,
        "fistbump.zip": 495,
        "flare.zip": 8408,
        "flaskoman.zip": 353,
        "flinthook.zip": 780,
        "flywrench.zip": 309,
        "fnafnes.zip": 2171,
        "forager.zip": 4389,
        "forgodden.zip": 2425,
        "formula_1_playdate.zip": 1319,
        "foxtower.zip": 3941,
        "franbow.zip": 554,
        "franken.zip": 1490,
        "freeciv.zip": 3054,
        "freecol.zip": 459,
        "freedink.zip": 1570,
        "freedom.planet.zip": 8034,
        "freedroid.zip": 6476,
        "freegemas.zip": 11629,
        "freegish.zip": 908,
        "freeserf.zip": 1954,
        "freesiege.zip": 805,
        "freesynd.zip": 1561,
        "fridaynightfunkin.zip": 7344,
        "frogfall.zip": 679,
        "frogger2.zip": 740,
        "frozen-bubble.zip": 4585,
        "fungusreaper.zip": 354,
        "galaxychampionstv.zip": 588,
        "galaxyforcesv2.zip": 890,
        "gameinfo.zip": 39800,
        "gardenstory.zip": 2379,
        "gatoroboto.zip": 2671,
        "gaugeofrage.zip": 392,
        "gaurodan.zip": 1024,
        "gcrash.zip": 2340,
        "gemrb.zip": 4794,
        "geometrystrike.zip": 1862,
        "ghostris.zip": 132,
        "gigalomania.zip": 5545,
        "globeba.zip": 7977,
        "gloomreducer.zip": 86,
        "gmu.music.player.zip": 6614,
        "gnurobbo.zip": 1332,
        "goblindungeoneer.zip": 164,
        "goinghomerevisited.zip": 2860,
        "goldenhornet.zip": 156,
        "goldminer.zip": 2132,
        "gooptygoo.zip": 167,
        "grafx2.zip": 1514,
        "gravityblocks.zip": 227,
        "gravitycircuit.zip": 7255,
        "gravitydefied.zip": 3705,
        "grazecountergm.zip": 206,
        "grelox.zip": 336,
        "grielsquest.zip": 400,
        "grimstorm.zip": 2180,
        "grizzland.zip": 45,
        "gta3.zip": 47377,
        "gtavc.zip": 59522,
        "guacamelee.zip": 2045,
        "gumchugirl.zip": 1693,
        "gumgem.zip": 1370,
        "gumgirlgb.zip": 1641,
        "gungungun.zip": 143,
        "gunroar.zip": 1060,
        "gunsandguns.zip": 849,
        "gyrobossdx.zip": 19,
        "hackgrid.zip": 47,
        "hakopalace.zip": 278,
        "half-life.zip": 66816,
        "hallowe_en.zip": 252,
        "hallowedcandy.zip": 563,
        "halloweenforever.zip": 195,
        "hallowseve.zip": 1842,
        "hammerwatch.zip": 794,
        "happyhills.zip": 654,
        "hatchwell.zip": 471,
        "hauntedlandsburial.zip": 348,
        "hawkisland.zip": 1072,
        "hawkthorne.zip": 4664,
        "heart.of.darkness.zip": 6008,
        "hebihebi.zip": 552,
        "heboris-sdl.zip": 2364,
        "hellfire.zip": 240,
        "help.no.brake.zip": 11889,
        "heroes.zip": 596,
        "hex-a-hop.zip": 2527,
        "hexen2.zip": 6443,
        "hftsr.zip": 9753,
        "hijinx.zip": 1749,
        "hikoban.zip": 58,
        "hocoslamfy.zip": 3120,
        "holonomy.zip": 2417,
        "holotzcastle.zip": 485,
        "honeyguardian.zip": 359,
        "hopowl.zip": 267,
        "hordes.zip": 344,
        "hota.zip": 2015,
        "hotlinesanzu.zip": 1126,
        "hoverboard.zip": 2398,
        "hovertank3d.zip": 279,
        "humming.out.zip": 610,
        "hunters.zip": 2785,
        "hurrican.zip": 4429,
        "hydorah.zip": 2604,
        "hydra.castle.labyrinth.zip": 7662,
        "hyper.jump.zip": 1140,
        "hyperfight.zip": 3623,
        "hyperlightdrifter.zip": 845,
        "hyperprincesspitch.zip": 560,
        "ichorous.zip": 664,
        "iconoclasts.zip": 12618,
        "icytower.zip": 3473,
        "igachahead.zip": 211,
        "iichantra_pear.zip": 5614,
        "iii.zip": 316,
        "images.000.zip": 98297,
        "images.001.zip": 67030,
        "images.002.zip": 66035,
        "images.003.zip": 71258,
        "images.004.zip": 101404,
        "images.005.zip": 113136,
        "images.006.zip": 10669,
        "images.007.zip": 3658,
        "images.008.zip": 4848,
        "images.009.zip": 2080,
        "images.zip": 617681,
        "imagestriker.zip": 168,
        "inertiablast.zip": 1110,
        "infested.zip": 700,
        "infra_arcana.zip": 1843,
        "interstatedrifter.zip": 360,
        "invaders.zip": 3348,
        "ioawn4t.zip": 2803,
        "ionfury.zip": 2560,
        "iortcw.zip": 19378,
        "iosas.zip": 1008,
        "ironferret.zip": 1591,
        "itcamefromtheforest.zip": 2594,
        "itta.zip": 369,
        "jazz2.zip": 5637,
        "jediacademy.zip": 12432,
        "jedioutcast.zip": 11530,
        "jestershelper.zip": 717,
        "jetlancer.zip": 897,
        "jetsetwilly.zip": 2202,
        "jugglrx.zip": 251,
        "jumpnbump.zip": 1748,
        "jumpoffthebridge.zip": 287,
        "jumponhead.zip": 82,
        "justanotherpong.zip": 2724,
        "justkisshimalready.zip": 40,
        "kaijubigbattel.zip": 407,
        "kaima.zip": 626,
        "kanon.zip": 651,
        "kemonorogue.zip": 2043,
        "kenslabyrinth.zip": 2775,
        "kikai.zip": 839,
        "kingofmachines.zip": 4630,
        "kleebuucravesfruitsalad.zip": 107,
        "klorets.zip": 702,
        "kobodeluxe.zip": 1388,
        "kuklomenos.zip": 538,
        "la-mulana.zip": 299,
        "labremnants.zip": 396,
        "labyrinthoflegendaryloot.zip": 2789,
        "laserkombat.zip": 1135,
        "lastmission.zip": 353,
        "lawnbusterforhire.zip": 216,
        "lbreakouthd.zip": 10799,
        "leapyear.zip": 145,
        "leftdeadspace.zip": 147,
        "legbreaker.zip": 608,
        "librespot.zip": 6888,
        "lierolibre.zip": 2320,
        "liltanks.zip": 321,
        "lineoff.zip": 468,
        "lisathebashful.zip": 619,
        "lisathehopeful.zip": 900,
        "lisathejoyful.zip": 1906,
        "lisathepainful.zip": 3106,
        "lisathepointless.zip": 733,
        "lisathetimeless.zip": 524,
        "lisatheunbreakable.zip": 691,
        "lisatheundone.zip": 562,
        "littlebusters.zip": 648,
        "littlefroggame.zip": 929,
        "littlegptracker.zip": 2112,
        "littlerunmo.zip": 6833,
        "lividmeadow.zip": 2632,
        "lizandlaz.zip": 80,
        "locust.zip": 743,
        "lode.zip": 1224,
        "loderunneronline.zip": 3334,
        "loguploader.zip": 59,
        "loopcat.zip": 788,
        "lose95.zip": 679,
        "lostethereal.zip": 159,
        "lostinsideact1.zip": 234,
        "lostpotato.zip": 423,
        "love.zip": 627,
        "love3.zip": 554,
        "lucid.zip": 462,
        "luck.be.a.landlord.zip": 2532,
        "lugaruhd.zip": 1191,
        "luminousslash.zip": 448,
        "lunarlux.zip": 458,
        "mableandthewood.zip": 1537,
        "magicalbroom.zip": 1217,
        "magicvigilante.zip": 729,
        "magnibox.zip": 414,
        "mago.zip": 1661,
        "maldita.castilla.zip": 22700,
        "manicminer.zip": 2553,
        "margot_beatrice_adventure.zip": 3768,
        "maskless.zip": 891,
        "maxdownforce.zip": 5014,
        "maximilien_adventure.zip": 6371,
        "meanderland.zip": 390,
        "meandmyshadow.zip": 2573,
        "megaball.zip": 427,
        "megaman.zip": 10401,
        "megamanx816-bit.zip": 6485,
        "megazeux.zip": 303,
        "mercenarykings.zip": 1158,
        "meritous.zip": 2719,
        "metanethunterg4.zip": 557,
        "mezzer.zip": 266,
        "microplatformer.zip": 434,
        "mightymike.zip": 1535,
        "milkinside.zip": 213,
        "mimisdeliverydash.zip": 1536,
        "mindustry.zip": 1497,
        "minesector.zip": 6275,
        "minetest.zip": 20819,
        "minidoom.zip": 2451,
        "minidoom2.zip": 3018,
        "minit.zip": 2871,
        "mire.zip": 5162,
        "mirrormagic.zip": 1512,
        "missdriller.zip": 4012,
        "missiledancer.zip": 465,
        "mobility.zip": 329,
        "mojotron.zip": 709,
        "monolith.zip": 323,
        "monsterbattlegrounds.zip": 171,
        "moonleap.zip": 157,
        "moonlight.zip": 16227,
        "moonlightnew.zip": 18231,
        "mr.boom.zip": 7442,
        "mreader.zip": 4470,
        "mrrescue.zip": 4845,
        "mslugsbf.zip": 3200,
        "multimanicminer.zip": 623,
        "multris.zip": 2958,
        "murtop.zip": 733,
        "must-have-been-the-wind.zip": 377,
        "mutant_tank_knights.zip": 922,
        "mystikbelle.zip": 1567,
        "mythos.zip": 3862,
        "nainainights.zip": 941,
        "nam.zip": 3288,
        "nanobounce.zip": 892,
        "nanosaur.zip": 1277,
        "nanosaur2.zip": 3974,
        "nebulus.zip": 3090,
        "neogensokyo.zip": 2107,
        "neoncityriders.zip": 1240,
        "ner.zip": 785,
        "netouchezpas5.zip": 87,
        "netsurf.zip": 11511,
        "neverball.zip": 9211,
        "nextdoor.zip": 622,
        "nfs2se.zip": 9566,
        "nidhogg.zip": 1919,
        "nightofelchupacabra.zip": 559,
        "nightshift.zip": 342,
        "nikwi.zip": 411,
        "njam.zip": 522,
        "nkaruga.zip": 6832,
        "noiz2sa.zip": 130,
        "nonny.zip": 7031,
        "nonstopspaceprobe.zip": 191,
        "noparachute.zip": 957,
        "notenoughtime.zip": 241,
        "nothing.zip": 1197,
        "notransmission.zip": 1136,
        "nova_pinball.zip": 5119,
        "npuzzle.zip": 1457,
        "nuclearthronemobile.zip": 9171,
        "nulldrifter.zip": 471,
        "nuvie.zip": 451,
        "nvpw.zip": 1239,
        "ocda.zip": 336,
        "oceansheart.zip": 5912,
        "oddworld.zip": 6777,
        "ofmiceandmoggies.zip": 155,
        "ohmygodlookatthisknight.zip": 399,
        "omegastrike.zip": 2599,
        "onceuponamobiusstrip.zip": 267,
        "onenighthotsprings.zip": 51,
        "openblok.zip": 7013,
        "openclaw.zip": 8476,
        "openenroth.zip": 200,
        "openfodder.zip": 4550,
        "openggs.zip": 3902,
        "openhexagon.zip": 149,
        "openjazz.zip": 11417,
        "openmohaa.zip": 582,
        "openmrac.zip": 6395,
        "opennotrium.zip": 205,
        "openomf.zip": 4884,
        "openrct2.zip": 5537,
        "opensupaplex.zip": 1951,
        "opensyobon.zip": 5429,
        "openttd.zip": 4239,
        "opentyrian.zip": 11818,
        "opentyrian2000.zip": 2434,
        "openxcom.zip": 4168,
        "operationsteel.zip": 352,
        "operius.zip": 2028,
        "oquonie.zip": 1400,
        "orthodon.zip": 49,
        "osanasrevenge.zip": 1551,
        "ottomatic.zip": 2936,
        "outlawn.zip": 161,
        "outofammo.zip": 4503,
        "overgun.zip": 1529,
        "owlboy.zip": 16678,
        "oxytone.zip": 147,
        "pachi.zip": 279,
        "pachycefalosaurus.zip": 212,
        "pacman.zip": 19449,
        "paintedheart.zip": 492,
        "panicroom.zip": 312,
        "panzerpaladin.zip": 6532,
        "parsec47.zip": 751,
        "passage.zip": 588,
        "paused.zip": 2544,
        "pekka-kana-2.zip": 2202,
        "penguincommand.zip": 457,
        "perfectdark.zip": 1516,
        "pigeon.zip": 3501,
        "pinball_disc_room.zip": 1569,
        "pingo.zip": 745,
        "pingus.zip": 1238,
        "pinky.zip": 166,
        "pippubaublequest.zip": 103,
        "pixeldescent.zip": 366,
        "pixelheat.zip": 4209,
        "plague.zip": 1717,
        "planetarian.zip": 770,
        "planetd4rk.zip": 708,
        "planetmerge.zip": 1843,
        "planetwaves.zip": 2111,
        "plaqueattackremake.zip": 898,
        "pleasedonttouchanything.zip": 243,
        "plumberssdl.zip": 926,
        "plunderislands.zip": 390,
        "pocketcrystalleague.zip": 7125,
        "pockettactics.zip": 6089,
        "pocketwondersport.zip": 2132,
        "pokewilds.zip": 789,
        "portmaster.zip": 76167,
        "postvoid.zip": 2412,
        "powder.zip": 5126,
        "powerlevel.zip": 1200,
        "powerputtlegend.zip": 1790,
        "ppengui.zip": 368,
        "prehistorik.2.zip": 5814,
        "prisnhax.zip": 54,
        "profadeluxe.zip": 4651,
        "prototype.zip": 6687,
        "psebay.zip": 5048,
        "psrl.zip": 2706,
        "pullywog.zip": 1493,
        "pulstario.zip": 308,
        "pupaipospacedx.zip": 244,
        "puremetal.zip": 467,
        "push.zip": 210,
        "putridshotultra.zip": 389,
        "puztrix_playdate.zip": 552,
        "pyk.zip": 282,
        "q2pro.zip": 969,
        "quadrupleback.zip": 241,
        "quake.2.zip": 16953,
        "quake.zip": 35348,
        "quake3.zip": 16286,
        "quakespasm.zip": 4469,
        "quester.zip": 40,
        "qyoblaster.zip": 208,
        "ragingblasters.zip": 526,
        "rakuen.zip": 3514,
        "rambleplanet.zip": 96,
        "randungeon.zip": 386,
        "raptor.zip": 9302,
        "ravenshike.zip": 183,
        "rawgl.zip": 12607,
        "reborn.zip": 6030,
        "rebound.zip": 707,
        "redhandsomehood.zip": 1240,
        "redneck.rampage.rides.again.zip": 4840,
        "redneck.rampage.zip": 6033,
        "redo.zip": 858,
        "redtrees.zip": 1221,
        "redtrianglesc.zip": 580,
        "rejuvenation.zip": 4904,
        "relichunters.zip": 935,
        "reminiscence.zip": 4505,
        "render96ex.zip": 25178,
        "residentvania.zip": 1333,
        "restore.portmaster.zip": 2940,
        "retrotime.zip": 2322,
        "revbros.zip": 474,
        "ri_li.zip": 3829,
        "rick.dangerous.zip": 11418,
        "rigelengine.zip": 2684,
        "riptale.zip": 483,
        "riskofrain.zip": 4900,
        "rite.zip": 697,
        "rlone.zip": 1007,
        "rlvm.zip": 1538,
        "road.invaders.zip": 2015,
        "roadwarriors2.zip": 169,
        "rockbot.zip": 1776,
        "rockdodger.zip": 681,
        "rockheads.zip": 624,
        "rocksndiamonds.zip": 3637,
        "roguelight.zip": 2819,
        "roguesentry.zip": 47,
        "roswyn.zip": 1180,
        "rota.zip": 17257,
        "rotationalshift.zip": 561,
        "rott.zip": 9750,
        "rrootage.zip": 1000,
        "runtimes.zip": 1,
        "russiansubwaydogs.zip": 1129,
        "rvgl.zip": 31320,
        "rwatch.zip": 413,
        "salvagette.zip": 278,
        "samuraibrothers.zip": 59,
        "santassurprise.zip": 818,
        "satlovecake.zip": 241,
        "satryn.zip": 2500,
        "savant.zip": 1944,
        "savingprincess.zip": 194,
        "sawa.zip": 273,
        "scaletheskulltower.zip": 450,
        "sdlbomber.zip": 779,
        "sdlpal.zip": 981,
        "sdlpop.zip": 14786,
        "sdlsopwith.zip": 1627,
        "sdlzombies.zip": 230,
        "secretteagarden.zip": 207,
        "septuple.zip": 540,
        "serioussam-tfe.zip": 8662,
        "serioussam-tse.zip": 8352,
        "sevenkingdoms.zip": 3211,
        "shadow.warrior.zip": 6687,
        "shadowwrangler.zip": 81,
        "shatteredpixeldungeon.zip": 507,
        "sheepo.zip": 347,
        "shippy.zip": 823,
        "shipwreck.zip": 2398,
        "shirobimetal.zip": 488,
        "shovel.knight.zip": 44401,
        "shovelknightpocketdungeon.zip": 1816,
        "shrubnaut.zip": 528,
        "siegeofosaka.zip": 2317,
        "signus.zip": 315,
        "simonsqrev.zip": 14570,
        "simplesokoban.zip": 6057,
        "simutrans.zip": 695,
        "skeletonboomerang.zip": 254,
        "skifree.zip": 6199,
        "skijump3.zip": 6205,
        "sm.zip": 8077,
        "smoothiegalaxy.zip": 5188,
        "smw.zip": 43,
        "smworld.zip": 12169,
        "snaklipse.zip": 1849,
        "sneakr.zip": 308,
        "sneggpit.zip": 1519,
        "snkrx.zip": 917,
        "snout.zip": 1099,
        "snowyland.zip": 184,
        "soh.zip": 24891,
        "soh2.zip": 11943,
        "sokobos.zip": 57,
        "sokobrawn.zip": 802,
        "somnokid.zip": 672,
        "sonic.1.zip": 12182,
        "sonic.2.zip": 10336,
        "sonic.cd.zip": 11480,
        "sonic.mania.zip": 32311,
        "sonic1sms.zip": 7190,
        "sonic2sms.zip": 5614,
        "sonic3air.zip": 4966,
        "sonic3sms.zip": 5671,
        "sonictimetwisted.zip": 4183,
        "sonictt16b.zip": 5354,
        "sorr.zip": 15277,
        "space.cadet.pinball.zip": 19689,
        "spacegladiators.zip": 458,
        "spacemothdx.zip": 463,
        "spacewingwar.zip": 178,
        "spearmintmountain.zip": 532,
        "spectralslash.zip": 532,
        "spellsling.zip": 1334,
        "spelltower.zip": 2934,
        "spellworm.zip": 67,
        "spelunky.zip": 30505,
        "spinch.zip": 404,
        "splinterzone.zip": 143,
        "spooky.zip": 946,
        "spookynakki.zip": 1027,
        "squeek.zip": 599,
        "srb2.zip": 18046,
        "srb2kart.zip": 15637,
        "starboy.zip": 1155,
        "starcatcher.zip": 6802,
        "stardewvalley.zip": 146516,
        "starfighter.zip": 144,
        "stargrovescramble.zip": 10615,
        "starvsthegame.zip": 882,
        "static.zip": 324,
        "steamlink.zip": 1162,
        "steelassault.zip": 7222,
        "stop_the_eggspress.zip": 567,
        "stoptheeggspress.zip": 13,
        "strangeadventures.zip": 2817,
        "streetsofclaus.zip": 1260,
        "strikeysisters.zip": 1362,
        "sudokul.zip": 5223,
        "sulka.zip": 1504,
        "sunsetshaped.zip": 1124,
        "sunsetwitchclassic.zip": 292,
        "super.mario.war.zip": 26464,
        "supercakeboy.zip": 974,
        "supercratebox.zip": 3070,
        "superdrome.bugs.zip": 481,
        "superdungeonmuncher.zip": 827,
        "supergaelicdodgeball.zip": 278,
        "superglitter.zip": 281,
        "superhexagon.zip": 821,
        "supermeatboy.zip": 10177,
        "supermegazero.zip": 271,
        "supermethanebros.zip": 808,
        "superraftboatclassic.zip": 771,
        "superrobotninjagirl.zip": 1194,
        "superskelemania.zip": 138,
        "superstarpath.zip": 770,
        "supertransball2.zip": 450,
        "supertux.zip": 9257,
        "supertuxkart.zip": 14254,
        "superxyx.zip": 1059,
        "swapwoodquestr.zip": 2518,
        "syasokoban.zip": 435,
        "tabletanks.zip": 279,
        "tailsadventure.zip": 5336,
        "tailspin.zip": 618,
        "tamashii.zip": 468,
        "tamatool.zip": 2322,
        "tamiku.zip": 150,
        "tantibus.zip": 294,
        "techmaniac.zip": 577,
        "templeofkashteki.zip": 700,
        "tempuslocus.zip": 418,
        "terminus.zip": 1570,
        "theaspect.zip": 320,
        "thecorruptionwithin.zip": 283,
        "thecurseofissyos.zip": 1990,
        "thefoundersofredacted.zip": 995,
        "thelegendoflumina.zip": 2497,
        "thermomorph.zip": 2457,
        "therush.zip": 348,
        "thestarlitescape.zip": 2257,
        "thesunandmoon.zip": 446,
        "thewind.zip": 153,
        "thextech.zip": 2736,
        "threecoins.zip": 1955,
        "thunderpunch.zip": 32,
        "thwack.zip": 2571,
        "thysword.zip": 290,
        "ticoban.zip": 261,
        "tileworld.zip": 4074,
        "timespinner.zip": 15010,
        "tiny-crate.zip": 7606,
        "tinystg.zip": 1939,
        "tinytowndefense.zip": 499,
        "tinyworldracing.zip": 174,
        "titan_tactics.zip": 7264,
        "titanion.zip": 402,
        "tmntsr.zip": 59642,
        "to_the_moon.zip": 6480,
        "tomb.raider.1.zip": 14689,
        "tomoyo_after.zip": 935,
        "topnep.zip": 1119,
        "touhoucirno.zip": 301,
        "towardsthepantheones.zip": 479,
        "towerbabe.zip": 1091,
        "towerbag.zip": 811,
        "towerfall.zip": 3709,
        "towerfortress.zip": 695,
        "toziuha.zip": 1805,
        "trianglerun.zip": 324,
        "trickykeys.zip": 1350,
        "trickykeys2.zip": 1047,
        "triggerrally.zip": 3278,
        "tripletrouble.zip": 317,
        "trogdorrb.zip": 1781,
        "trolley.delayma.zip": 501,
        "tsunderswap.zip": 562,
        "tube64.zip": 4198,
        "tumbledown.zip": 305,
        "tumikifighters.zip": 682,
        "tunics.zip": 2407,
        "turbotabletennis.zip": 2054,
        "tuxfootball.zip": 1508,
        "tuxpuck.zip": 1163,
        "tvruhh.zip": 460,
        "twodie.zip": 305,
        "ubermoshcollection.zip": 859,
        "udlrmodify.zip": 1038,
        "udongeinx.zip": 354,
        "ufo50.zip": 15466,
        "ultimatestunts.zip": 5008,
        "ultimatetapankaikki.zip": 2160,
        "undergrave.zip": 427,
        "undertale.zip": 40849,
        "ungratefulbirdsngd.zip": 131,
        "unlikely.zip": 892,
        "upo.zip": 1985,
        "uqm.zip": 4946,
        "utyellow.zip": 5681,
        "valhalla.zip": 4917,
        "vanillara.zip": 8275,
        "vanillatd.zip": 5740,
        "vcmi.zip": 11223,
        "vdrift.zip": 3406,
        "verticaldropheroeshd.zip": 272,
        "vhr.zip": 4639,
        "vikingsofmidgard.zip": 3125,
        "viralreload.zip": 266,
        "vitasnake.zip": 993,
        "vnds-love.zip": 598,
        "vodovod.zip": 795,
        "voidbreach.zip": 149,
        "voidpyramid.zip": 359,
        "voidstranger.zip": 1274,
        "vortexion.zip": 960,
        "vvvvvv.zip": 19405,
        "wakingmars.zip": 868,
        "walthrosrenewal.zip": 150,
        "waternet.zip": 2028,
        "wetspot2.zip": 1206,
        "widelands.zip": 4881,
        "willyousnail.zip": 216,
        "wipeout.zip": 8952,
        "wizardchase.zip": 2574,
        "wizardorb.zip": 569,
        "wizznic.zip": 1026,
        "wolf3d.zip": 10045,
        "wordlesdl.zip": 4476,
        "wordswithfreds.zip": 1919,
        "world.war.ii.gi.zip": 4359,
        "worldofgoo.zip": 5851,
        "worship_vector.zip": 2001,
        "wuppo.zip": 621,
        "xenofightersr.zip": 2120,
        "xenonvalkyrie.zip": 2447,
        "xmoto.zip": 1663,
        "xooxenoxafari.zip": 142,
        "xye.zip": 379,
        "yarntown.zip": 2355,
        "yarsrevenge.zip": 46,
        "yatka.zip": 11109,
        "yellowjacket.zip": 593,
        "yolkheroes.zip": 937,
        "youdiedbanry.zip": 472,
        "youhave10s2023.zip": 598,
        "z-warp.zip": 399,
        "zelda-bookofmudora.zip": 3569,
        "zelda-mercurischest.zip": 1703,
        "zelda-mysteryofsolarusdx.zip": 3836,
        "zelda-mysteryofsolarusxd.zip": 2399,
        "zelda-roth-se.zip": 2996,
        "zelda3.zip": 9037,
        "zelda3t.zip": 1322,
        "zelda_roth.zip": 1396,
        "zeldadoi.zip": 1742,
        "zeldansq.zip": 1365,
        "zeldaolb.zip": 16730,
        "zeldaxd-mercurischess.zip": 3129,
        "zeldoschallenge.zip": 2389,
        "zeldoschallenge2.zip": 2957,
        "zeroptianinvasion.zip": 285,
        "zeroranger.zip": 2806,
        "zgloom.zip": 6121,
        "ziggurat.zip": 978,
        "ziiaol.zip": 3561,
        "znax.zip": 3059
    },
    "total_downloads": 3676600
}